MANIFEST.in
README.rst
setup.py
version.py
pyray/__init__.py
pyray/__init__.pyi
raylib/__init__.py
raylib/__init__.pyi
raylib/colors.py
raylib/defines.py
raylib/enums.py
raylib/libraylib.dylib
raylib/libraylib.so
raylib/raylib.dll
raylib/raylib_modified.h
raylib/version.py
raylib_dynamic.egg-info/PKG-INFO
raylib_dynamic.egg-info/SOURCES.txt
raylib_dynamic.egg-info/dependency_links.txt
raylib_dynamic.egg-info/requires.txt
raylib_dynamic.egg-info/top_level.txt