Metadata-Version: 2.1
Name: raylib-dynamic
Version: 5.0.0.1
Summary: Python CFFI bindings for Raylib DLL version
Home-page: https://github.com/electronstudio/raylib-python-cffi
Author: Electron Studio
Author-email: github@electronstudio.co.uk
License: EPL-2.0
Classifier: License :: OSI Approved :: Eclipse Public License 2.0 (EPL-2.0)
Classifier: Programming Language :: Python :: 3
Classifier: Programming Language :: Python :: 3.10
Classifier: Programming Language :: Python :: 3.9
Classifier: Programming Language :: Python :: 3.8
Classifier: Programming Language :: Python :: 3.6
Classifier: Programming Language :: Python :: 3.7
